poola_be/__init__.py
poola_be/_nbdev.py
poola_be/core.py
poola_be-0.0.1.dist-info/LICENSE
poola_be-0.0.1.dist-info/METADATA
poola_be-0.0.1.dist-info/WHEEL
poola_be-0.0.1.dist-info/entry_points.txt
poola_be-0.0.1.dist-info/top_level.txt
poola_be-0.0.1.dist-info/RECORD
