Metadata-Version: 2.1
Name: poola-be
Version: 0.0.1
Summary: Python package to analyze the results of base editor screens
Home-page: https://github.com/gpprnd/poola_be/tree/master/
Author: Mudra Hegde
Author-email: mhegde@broadinstitute.org
License: Apache Software License 2.0
Keywords: CRISPR,python,base editor
Platform: UNKNOWN
Classifier: Development Status :: 3 - Alpha
Classifier: Intended Audience :: Developers
Classifier: Natural Language :: English
Classifier: Programming Language :: Python :: 3.6
Classifier: Programming Language :: Python :: 3.7
Classifier: Programming Language :: Python :: 3.8
Classifier: License :: OSI Approved :: Apache Software License
Requires-Python: >=3.6
Requires-Dist: numpy (>=1.19.5)
Requires-Dist: pandas (>=1.0.0)
Requires-Dist: scikit-learn (>=0.24.1)
